orgcrawler/crawlers.py
orgcrawler/logger.py
orgcrawler/orgs.py
orgcrawler/payloads.py
orgcrawler/utils.py
orgcrawler/cli/orgcrawler.py
orgcrawler/cli/orgquery.py
orgcrawler/cli/utils.py
orgcrawler/mock/__init__.py
orgcrawler/mock/org.py
orgcrawler/mock/payload.py
orgcrawler-1.0.0a6.dist-info/LICENSE
orgcrawler-1.0.0a6.dist-info/METADATA
orgcrawler-1.0.0a6.dist-info/WHEEL
orgcrawler-1.0.0a6.dist-info/entry_points.txt
orgcrawler-1.0.0a6.dist-info/top_level.txt
orgcrawler-1.0.0a6.dist-info/RECORD
