Metadata-Version: 2.1
Name: orgcrawler
Version: 1.0.0a6
Summary: Tools for working with AWS Organizations
Home-page: https://github.com/ucopacme/orgcrawler
Author: Ashley Gould - University of California Office of the President
Author-email: agould@ucop.edu
License: GPLv3
Project-URL: Documentation, https://orgcrawler.readthedocs.io/en/latest/
Project-URL: Issues, https://github.com/ucopacme/orgcrawler/issues
Keywords: aws organizations boto3
Platform: UNKNOWN
Classifier: Development Status :: 3 - Alpha
Classifier: Intended Audience :: Developers
Classifier: Intended Audience :: System Administrators
Classifier: License :: OSI Approved :: GNU General Public License v3 or later (GPLv3+)
Classifier: Programming Language :: Python :: 3.6
Classifier: Programming Language :: Python :: 3.7
Requires-Dist: botocore
Requires-Dist: boto3
Requires-Dist: PyYAML
Requires-Dist: click
